szn_url/__init__.py
szn_url-1.0.2.dist-info/METADATA
szn_url-1.0.2.dist-info/WHEEL
szn_url-1.0.2.dist-info/entry_points.txt
szn_url-1.0.2.dist-info/top_level.txt
szn_url-1.0.2.dist-info/RECORD
