Metadata-Version: 2.2
Name: szn_url
Version: 1.0.2
Summary: A demo package that downloads OS-specific and test manuals on initialization.
Home-page: https://example.com/szn_url
Author: Pen Test
Author-email: test.skvara2@seznam.cz
Dynamic: author
Dynamic: author-email
Dynamic: home-page
Dynamic: summary
